__init__.py
openchord.py
openchord-0.1.7.dist-info/LICENSE
openchord-0.1.7.dist-info/METADATA
openchord-0.1.7.dist-info/WHEEL
openchord-0.1.7.dist-info/top_level.txt
openchord-0.1.7.dist-info/RECORD
