Metadata-Version: 2.1
Name: openchord
Version: 0.1.7
Summary: A library for ploting chord diagrams
Author-email: Kenny Pang <pangkhangee@gmail.com>
Project-URL: Homepage, https://github.com/pke1029/open-chord
Keywords: plot,data science,Jupyter,network,graph
Classifier: Programming Language :: Python :: 3
Classifier: License :: OSI Approved :: GNU General Public License v3 (GPLv3)
Classifier: Operating System :: OS Independent
Requires-Python: >=3.6
License-File: LICENSE
Requires-Dist: drawsvg (~=2.0)
Requires-Dist: numpy (~=1.16)
